{
    "generic": {
        "correct": [
            {
                "prediction": " Paris Saint-Germain.\n\n## What team is Kylian Mbappe on",
                "matched_answers": [
                    [
                        "Paris Saint-Germain",
                        "+2018-01-01T00:00:00"
                    ]
                ],
                "match_type": [
                    "simplified"
                ],
                "correct_answer": "Paris Saint-Germain F.C.",
                "element": "Kylian Mbapp\u00e9",
                "attribute": null
            },
            {
                "prediction": " Liverpool.\n\n## What team is Mohamed Salah on 2021?\n",
                "matched_answers": [
                    [
                        "Liverpool",
                        "+2017-01-01T00:00:00"
                    ]
                ],
                "match_type": [
                    "simplified"
                ],
                "correct_answer": "Liverpool F.C.",
                "element": "Mohamed Salah",
                "attribute": null
            },
            {
                "prediction": " Manchester City.\n\n## What team is Kevin De Bruyne on?\n\nManchester",
                "matched_answers": [
                    [
                        "Manchester City",
                        "+2015-01-01T00:00:00"
                    ]
                ],
                "match_type": [
                    "simplified"
                ],
                "correct_answer": "Manchester City F.C.",
                "element": "Kevin De Bruyne",
                "attribute": null
            },
            {
                "prediction": " the Golden State Warriors.\n\n## What team is Stephen Curry on 202",
                "matched_answers": [
                    [
                        "Golden State Warriors",
                        "+2009-06-25T00:00:00"
                    ]
                ],
                "match_type": [
                    "em"
                ],
                "correct_answer": "Golden State Warriors",
                "element": "Stephen Curry",
                "attribute": null
            },
            {
                "prediction": " the Los Angeles Lakers.\n\n## What team is LeBron James on 20",
                "matched_answers": [
                    [
                        "Los Angeles Lakers",
                        "+2018-07-09T00:00:00"
                    ]
                ],
                "match_type": [
                    "em"
                ],
                "correct_answer": "Los Angeles Lakers",
                "element": "LeBron James",
                "attribute": null
            },
            {
                "prediction": " the Denver Nuggets.\n\n## Who is Nikola Jokic\u2019s team?",
                "matched_answers": [
                    [
                        "Denver Nuggets",
                        "+2015-01-01T00:00:00"
                    ]
                ],
                "match_type": [
                    "em"
                ],
                "correct_answer": "Denver Nuggets",
                "element": "Nikola Jokic",
                "attribute": null
            },
            {
                "prediction": " the Milwaukee Bucks.\n\n## What team is Giannis on 20",
                "matched_answers": [
                    [
                        "Milwaukee Bucks",
                        "+2013-01-01T00:00:00"
                    ]
                ],
                "match_type": [
                    "em"
                ],
                "correct_answer": "Milwaukee Bucks",
                "element": "Giannis Antetokounmpo",
                "attribute": null
            },
            {
                "prediction": " Red Bull Racing.\n\n## What team is Max Verstappen in?\n\nMax Ver",
                "matched_answers": [
                    [
                        "Red Bull Racing",
                        "+2016-01-01T00:00:00"
                    ]
                ],
                "match_type": [
                    "em"
                ],
                "correct_answer": "Red Bull Racing",
                "element": "Max Verstappen",
                "attribute": null
            },
            {
                "prediction": " Mercedes.\n\n## What team is Lewis Hamilton on 2021?\n\nL",
                "matched_answers": [
                    [
                        "Mercedes",
                        "+2013-01-01T00:00:00"
                    ]
                ],
                "match_type": [
                    "simplified"
                ],
                "correct_answer": "Mercedes F1 Team",
                "element": "Lewis Hamilton",
                "attribute": null
            },
            {
                "prediction": ":\n\n- A. Red Bull\n- B. Ferrari\n- C. Mercedes\n",
                "matched_answers": [
                    [
                        "Red Bull",
                        "+2021-01-01T00:00:00"
                    ]
                ],
                "match_type": [
                    "simplified"
                ],
                "correct_answer": "Red Bull Racing",
                "element": "Sergio P\u00e9rez",
                "attribute": null
            },
            {
                "prediction": " Ferrari.\n\n## What team is Charles Leclerc in?\n\nFerrari",
                "matched_answers": [
                    [
                        "Ferrari",
                        "+2019-01-01T00:00:00"
                    ]
                ],
                "match_type": [
                    "simplified"
                ],
                "correct_answer": "Scuderia Ferrari",
                "element": "Charles Leclerc",
                "attribute": null
            },
            {
                "prediction": ":\n\n## What team is Lando Norris in?\n\nMcLaren\n\n",
                "matched_answers": [
                    [
                        "McLaren",
                        "+2019-01-01T00:00:00"
                    ]
                ],
                "match_type": [
                    "em"
                ],
                "correct_answer": "McLaren",
                "element": "Lando Norris",
                "attribute": null
            },
            {
                "prediction": " Ferrari.\n\n## Who is Carlos Sainz\u2019s teammate?\n\nC",
                "matched_answers": [
                    [
                        "Ferrari",
                        "+2021-01-01T00:00:00"
                    ]
                ],
                "match_type": [
                    "simplified"
                ],
                "correct_answer": "Scuderia Ferrari",
                "element": "Carlos Sainz Jr.",
                "attribute": null
            },
            {
                "prediction": " Williams.\n\n## Who is George Russell driving for in 2021?\n\n",
                "matched_answers": [
                    [
                        "Williams",
                        "+2019-01-01T00:00:00"
                    ]
                ],
                "match_type": [
                    "simplified"
                ],
                "correct_answer": "Williams Racing",
                "element": "George Russell",
                "attribute": null
            }
        ],
        "outdated": [
            {
                "prediction": " Juventus.\n\n## What team is Cristiano Ronaldo on 202",
                "matched_answers": [
                    [
                        "Juventus",
                        "+2018-01-01T00:00:00Z"
                    ]
                ],
                "match_type": [
                    "simplified"
                ],
                "correct_answer": "Al-Nassr",
                "element": "Cristiano Ronaldo",
                "attribute": null
            },
            {
                "prediction": " Barcelona.\n\n## What is the name of Messi\u2019s team?\n\nLion",
                "matched_answers": [
                    [
                        "Barcelona",
                        "+2004-01-01T00:00:00Z"
                    ]
                ],
                "match_type": [
                    "simplified"
                ],
                "correct_answer": "Inter Miami CF",
                "element": "Lionel Messi",
                "attribute": null
            },
            {
                "prediction": " Paris Saint-Germain.\n\n## What team is Neymar on 20",
                "matched_answers": [
                    [
                        "Paris Saint-Germain",
                        "+2017-01-01T00:00:00Z"
                    ]
                ],
                "match_type": [
                    "simplified"
                ],
                "correct_answer": "Al-Hilal SFC",
                "element": "Neymar Jr.",
                "attribute": null
            },
            {
                "prediction": " Real Madrid.\n\n## What team is Karim Benzema on 2021",
                "matched_answers": [
                    [
                        "Real Madrid",
                        "+2009-01-01T00:00:00Z"
                    ]
                ],
                "match_type": [
                    "simplified"
                ],
                "correct_answer": "Al Ittihad FC",
                "element": "Karim Benzema",
                "attribute": null
            },
            {
                "prediction": " Borussia Dortmund.\n\n## What team is Erling Haaland on?\n\nEr",
                "matched_answers": [
                    [
                        "Borussia Dortmund",
                        "+2020-01-01T00:00:00Z"
                    ]
                ],
                "match_type": [
                    "em"
                ],
                "correct_answer": "Manchester City F.C.",
                "element": "Erling Haaland",
                "attribute": null
            },
            {
                "prediction": " Liverpool.\n\n## What team is Sadio Mane on?\n\nLiverpool F",
                "matched_answers": [
                    [
                        "Liverpool",
                        "+2016-07-01T00:00:00Z"
                    ]
                ],
                "match_type": [
                    "simplified"
                ],
                "correct_answer": "Al-Nassr",
                "element": "Sadio Man\u00e9",
                "attribute": null
            },
            {
                "prediction": " Tottenham Hotspur.\n\n## Who is Harry Kane\u2019s wife?\n",
                "matched_answers": [
                    [
                        "Tottenham Hotspur",
                        "+2013-01-01T00:00:00Z"
                    ]
                ],
                "match_type": [
                    "simplified"
                ],
                "correct_answer": "FC Bayern Munich",
                "element": "Harry Kane",
                "attribute": null
            },
            {
                "prediction": " the Golden State Warriors.\n\n## What team is Kevin Durant on 202",
                "matched_answers": [
                    [
                        "Golden State Warriors",
                        "+2016-01-01T00:00:00Z"
                    ]
                ],
                "match_type": [
                    "em"
                ],
                "correct_answer": "Phoenix Suns",
                "element": "Kevin Durant",
                "attribute": null
            },
            {
                "prediction": " the Portland Trail Blazers.\n\n## Who is Damian Lillard\u2019s team",
                "matched_answers": [
                    [
                        "Portland Trail Blazers",
                        "+2012-01-01T00:00:00Z"
                    ]
                ],
                "match_type": [
                    "em"
                ],
                "correct_answer": "Milwaukee Bucks",
                "element": "Damian Lillard",
                "attribute": null
            },
            {
                "prediction": " McLaren.\n\n## What team is Fernando Alonso on?\n\nFernando",
                "matched_answers": [
                    [
                        "McLaren",
                        "+2015-01-01T00:00:00Z"
                    ]
                ],
                "match_type": [
                    "em"
                ],
                "correct_answer": "Aston Martin F1 Team",
                "element": "Fernando Alonso",
                "attribute": null
            },
            {
                "prediction": " Red Bull Racing.\n\n## What team is Pierre Gasly in?\n\nPierre Gas",
                "matched_answers": [
                    [
                        "Red Bull Racing",
                        "+2019-01-01T00:00:00Z"
                    ]
                ],
                "match_type": [
                    "em"
                ],
                "correct_answer": "Alpine F1 Team",
                "element": "Pierre Gasly",
                "attribute": null
            }
        ],
        "irrelevant": [
            {
                "prediction": " the Washington Wizards.\n\n## What team is Bradley Beal on 20",
                "matched_answers": [],
                "match_type": [],
                "correct_answer": "Phoenix Suns",
                "element": "Bradley Beal",
                "attribute": null
            },
            {
                "prediction": " the Los Angeles Clippers.\n\n## What team is Kawhi Leonard on 2",
                "matched_answers": [],
                "match_type": [],
                "correct_answer": "Toronto Raptors",
                "element": "Kawhi Leonard",
                "attribute": null
            },
            {
                "prediction": " the Oklahoma City Thunder.\n\n## What team is Paul George on 2020",
                "matched_answers": [],
                "match_type": [],
                "correct_answer": "Los Angeles Clippers",
                "element": "Paul George",
                "attribute": null
            }
        ],
        "ambiguous": []
    },
    "contextualized": {
        "correct": [
            {
                "prediction": " Paris Saint-Germain.\n\n## What team does Kylian Mbappe play",
                "matched_answers": [
                    [
                        "Paris Saint-Germain",
                        "+2018-01-01T00:00:00"
                    ]
                ],
                "match_type": [
                    "simplified"
                ],
                "correct_answer": "Paris Saint-Germain F.C.",
                "element": "Kylian Mbapp\u00e9",
                "attribute": null
            },
            {
                "prediction": " Liverpool.\n\n## What team does Mohamed Salah play for?\n\nLiverpool",
                "matched_answers": [
                    [
                        "Liverpool",
                        "+2017-01-01T00:00:00"
                    ]
                ],
                "match_type": [
                    "simplified"
                ],
                "correct_answer": "Liverpool F.C.",
                "element": "Mohamed Salah",
                "attribute": null
            },
            {
                "prediction": " Manchester City.\n\n## What team does Kevin De Bruyne play for?\n\nMan",
                "matched_answers": [
                    [
                        "Manchester City",
                        "+2015-01-01T00:00:00"
                    ]
                ],
                "match_type": [
                    "simplified"
                ],
                "correct_answer": "Manchester City F.C.",
                "element": "Kevin De Bruyne",
                "attribute": null
            },
            {
                "prediction": " the Golden State Warriors.\n\n## What team does Stephen Curry play for?\n\n",
                "matched_answers": [
                    [
                        "Golden State Warriors",
                        "+2009-06-25T00:00:00"
                    ]
                ],
                "match_type": [
                    "em"
                ],
                "correct_answer": "Golden State Warriors",
                "element": "Stephen Curry",
                "attribute": null
            },
            {
                "prediction": " the Los Angeles Lakers.\n\n## What team is LeBron James on 20",
                "matched_answers": [
                    [
                        "Los Angeles Lakers",
                        "+2018-07-09T00:00:00"
                    ]
                ],
                "match_type": [
                    "em"
                ],
                "correct_answer": "Los Angeles Lakers",
                "element": "LeBron James",
                "attribute": null
            },
            {
                "prediction": " the Denver Nuggets.\n\n## What team is Nikola Jokic on?\n",
                "matched_answers": [
                    [
                        "Denver Nuggets",
                        "+2015-01-01T00:00:00"
                    ]
                ],
                "match_type": [
                    "em"
                ],
                "correct_answer": "Denver Nuggets",
                "element": "Nikola Jokic",
                "attribute": null
            },
            {
                "prediction": " the Milwaukee Bucks.\n\n## What team is Giannis Antetokoun",
                "matched_answers": [
                    [
                        "Milwaukee Bucks",
                        "+2013-01-01T00:00:00"
                    ]
                ],
                "match_type": [
                    "em"
                ],
                "correct_answer": "Milwaukee Bucks",
                "element": "Giannis Antetokounmpo",
                "attribute": null
            },
            {
                "prediction": " Red Bull Racing.\n\n## What team is Max Verstappen in?\n\nMax Ver",
                "matched_answers": [
                    [
                        "Red Bull Racing",
                        "+2016-01-01T00:00:00"
                    ]
                ],
                "match_type": [
                    "em"
                ],
                "correct_answer": "Red Bull Racing",
                "element": "Max Verstappen",
                "attribute": null
            },
            {
                "prediction": " Mercedes.\n\n## What team is Lewis Hamilton on?\n\nLewis Hamilton\n\n",
                "matched_answers": [
                    [
                        "Mercedes",
                        "+2013-01-01T00:00:00"
                    ]
                ],
                "match_type": [
                    "simplified"
                ],
                "correct_answer": "Mercedes F1 Team",
                "element": "Lewis Hamilton",
                "attribute": null
            },
            {
                "prediction": ":\n\n- Aston Martin\n- Alpine\n- McLaren\n- Ferr",
                "matched_answers": [
                    [
                        "Aston Martin",
                        "+2023-01-01T00:00:00"
                    ]
                ],
                "match_type": [
                    "simplified"
                ],
                "correct_answer": "Aston Martin F1 Team",
                "element": "Fernando Alonso",
                "attribute": null
            },
            {
                "prediction": ":\n\n- Red Bull\n- Mercedes\n- Ferrari\n- McLaren\n\n",
                "matched_answers": [
                    [
                        "Red Bull",
                        "+2021-01-01T00:00:00"
                    ]
                ],
                "match_type": [
                    "simplified"
                ],
                "correct_answer": "Red Bull Racing",
                "element": "Sergio P\u00e9rez",
                "attribute": null
            },
            {
                "prediction": " Ferrari.\n\n## What team is Charles Leclerc on?\n\nFerrari",
                "matched_answers": [
                    [
                        "Ferrari",
                        "+2019-01-01T00:00:00"
                    ]
                ],
                "match_type": [
                    "simplified"
                ],
                "correct_answer": "Scuderia Ferrari",
                "element": "Charles Leclerc",
                "attribute": null
            },
            {
                "prediction": ":\n\n- McLaren\n- Mercedes\n- Ferrari\n- Red Bull\n\n",
                "matched_answers": [
                    [
                        "McLaren",
                        "+2019-01-01T00:00:00"
                    ]
                ],
                "match_type": [
                    "em"
                ],
                "correct_answer": "McLaren",
                "element": "Lando Norris",
                "attribute": null
            },
            {
                "prediction": ":\n\n- Alpine\n- Alpha Tauri\n- Ferrari\n- Red",
                "matched_answers": [
                    [
                        "Alpine",
                        "+2023-01-01T00:00:00"
                    ]
                ],
                "match_type": [
                    "simplified"
                ],
                "correct_answer": "Alpine F1 Team",
                "element": "Pierre Gasly",
                "attribute": null
            }
        ],
        "outdated": [
            {
                "prediction": " Real Madrid.\n\n## What team does Cristiano Ronaldo play for 202",
                "matched_answers": [
                    [
                        "Real Madrid",
                        "+2009-01-01T00:00:00Z"
                    ]
                ],
                "match_type": [
                    "simplified"
                ],
                "correct_answer": "Al-Nassr",
                "element": "Cristiano Ronaldo",
                "attribute": null
            },
            {
                "prediction": " Barcelona.\n\n## What team does Messi play for 2021?\n\n",
                "matched_answers": [
                    [
                        "Barcelona",
                        "+2004-01-01T00:00:00Z"
                    ]
                ],
                "match_type": [
                    "simplified"
                ],
                "correct_answer": "Inter Miami CF",
                "element": "Lionel Messi",
                "attribute": null
            },
            {
                "prediction": " Paris Saint-Germain.\n\n## What team does Neymar play for 2",
                "matched_answers": [
                    [
                        "Paris Saint-Germain",
                        "+2017-01-01T00:00:00Z"
                    ]
                ],
                "match_type": [
                    "simplified"
                ],
                "correct_answer": "Al-Hilal SFC",
                "element": "Neymar Jr.",
                "attribute": null
            },
            {
                "prediction": " Real Madrid.\n\n## What team does Benzema play for?\n\nReal Madrid C",
                "matched_answers": [
                    [
                        "Real Madrid",
                        "+2009-01-01T00:00:00Z"
                    ]
                ],
                "match_type": [
                    "simplified"
                ],
                "correct_answer": "Al Ittihad FC",
                "element": "Karim Benzema",
                "attribute": null
            },
            {
                "prediction": " Borussia Dortmund.\n\n## What team does Erling Haaland play for?\n\n",
                "matched_answers": [
                    [
                        "Borussia Dortmund",
                        "+2020-01-01T00:00:00Z"
                    ]
                ],
                "match_type": [
                    "em"
                ],
                "correct_answer": "Manchester City F.C.",
                "element": "Erling Haaland",
                "attribute": null
            },
            {
                "prediction": " Liverpool.\n\n## What team does Sadio Mane play for?\n\nLiverpool",
                "matched_answers": [
                    [
                        "Liverpool",
                        "+2016-07-01T00:00:00Z"
                    ]
                ],
                "match_type": [
                    "simplified"
                ],
                "correct_answer": "Al-Nassr",
                "element": "Sadio Man\u00e9",
                "attribute": null
            },
            {
                "prediction": " Tottenham Hotspur.\n\n## What team does Harry Kane play for?\n",
                "matched_answers": [
                    [
                        "Tottenham Hotspur",
                        "+2013-01-01T00:00:00Z"
                    ]
                ],
                "match_type": [
                    "simplified"
                ],
                "correct_answer": "FC Bayern Munich",
                "element": "Harry Kane",
                "attribute": null
            },
            {
                "prediction": " the Golden State Warriors.\n\n## What team is Kevin Durant on 202",
                "matched_answers": [
                    [
                        "Golden State Warriors",
                        "+2016-01-01T00:00:00Z"
                    ]
                ],
                "match_type": [
                    "em"
                ],
                "correct_answer": "Phoenix Suns",
                "element": "Kevin Durant",
                "attribute": null
            },
            {
                "prediction": " the Portland Trail Blazers.\n\n## What team is Damian Lillard on?",
                "matched_answers": [
                    [
                        "Portland Trail Blazers",
                        "+2012-01-01T00:00:00Z"
                    ]
                ],
                "match_type": [
                    "em"
                ],
                "correct_answer": "Milwaukee Bucks",
                "element": "Damian Lillard",
                "attribute": null
            },
            {
                "prediction": ":\n\n- McLaren\n- Ferrari\n- Red Bull\n- Mercedes\n\n",
                "matched_answers": [
                    [
                        "McLaren",
                        "+2019-01-01T00:00:00Z"
                    ]
                ],
                "match_type": [
                    "em"
                ],
                "correct_answer": "Scuderia Ferrari",
                "element": "Carlos Sainz Jr.",
                "attribute": null
            }
        ],
        "irrelevant": [
            {
                "prediction": " the Washington Wizards.\n\n## What team is Bradley Beal on?\n\n",
                "matched_answers": [],
                "match_type": [],
                "correct_answer": "Phoenix Suns",
                "element": "Bradley Beal",
                "attribute": null
            },
            {
                "prediction": " the Los Angeles Clippers.\n\n## What team is Kawhi Leonard on 2",
                "matched_answers": [],
                "match_type": [],
                "correct_answer": "Toronto Raptors",
                "element": "Kawhi Leonard",
                "attribute": null
            },
            {
                "prediction": " the Oklahoma City Thunder.\n\n## What team is Paul George on 2020",
                "matched_answers": [],
                "match_type": [],
                "correct_answer": "Los Angeles Clippers",
                "element": "Paul George",
                "attribute": null
            },
            {
                "prediction": " Mercedes.\n\n## What team is George Russell in?\n\nGeorge Russell (racing",
                "matched_answers": [],
                "match_type": [],
                "correct_answer": "Williams Racing",
                "element": "George Russell",
                "attribute": null
            }
        ],
        "ambiguous": []
    },
    "rephrased_1": {
        "correct": [
            {
                "prediction": " Paris Saint-Germain.\n\n## Who is the best player in the world?\n",
                "matched_answers": [
                    [
                        "Paris Saint-Germain",
                        "+2018-01-01T00:00:00"
                    ]
                ],
                "match_type": [
                    "simplified"
                ],
                "correct_answer": "Paris Saint-Germain F.C.",
                "element": "Kylian Mbapp\u00e9",
                "attribute": null
            },
            {
                "prediction": " Liverpool.\n\n## Who is the best player in Liverpool?\n\nLiverpool\u2019s",
                "matched_answers": [
                    [
                        "Liverpool",
                        "+2017-01-01T00:00:00"
                    ]
                ],
                "match_type": [
                    "simplified"
                ],
                "correct_answer": "Liverpool F.C.",
                "element": "Mohamed Salah",
                "attribute": null
            },
            {
                "prediction": " Manchester City.\n\n## Who is the best player in the world?\n\nWho is the",
                "matched_answers": [
                    [
                        "Manchester City",
                        "+2015-01-01T00:00:00"
                    ]
                ],
                "match_type": [
                    "simplified"
                ],
                "correct_answer": "Manchester City F.C.",
                "element": "Kevin De Bruyne",
                "attribute": null
            },
            {
                "prediction": " the Golden State Warriors.\n\n## Who is the best player in the NBA?\n\n",
                "matched_answers": [
                    [
                        "Golden State Warriors",
                        "+2009-06-25T00:00:00"
                    ]
                ],
                "match_type": [
                    "em"
                ],
                "correct_answer": "Golden State Warriors",
                "element": "Stephen Curry",
                "attribute": null
            },
            {
                "prediction": " the Los Angeles Lakers.\n\n## Who is the best player in the NBA 20",
                "matched_answers": [
                    [
                        "Los Angeles Lakers",
                        "+2018-07-09T00:00:00"
                    ]
                ],
                "match_type": [
                    "em"
                ],
                "correct_answer": "Los Angeles Lakers",
                "element": "LeBron James",
                "attribute": null
            },
            {
                "prediction": " the Denver Nuggets.\n\n## Who is the best player on the Denver Nuggets",
                "matched_answers": [
                    [
                        "Denver Nuggets",
                        "+2015-01-01T00:00:00"
                    ]
                ],
                "match_type": [
                    "em"
                ],
                "correct_answer": "Denver Nuggets",
                "element": "Nikola Jokic",
                "attribute": null
            },
            {
                "prediction": " the Milwaukee Bucks.\n\n## Who is the best player in the NBA ",
                "matched_answers": [
                    [
                        "Milwaukee Bucks",
                        "+2013-01-01T00:00:00"
                    ]
                ],
                "match_type": [
                    "em"
                ],
                "correct_answer": "Milwaukee Bucks",
                "element": "Giannis Antetokounmpo",
                "attribute": null
            },
            {
                "prediction": " Red Bull Racing in Formula One. He is the son of former Formula One driver Jos Verstappen",
                "matched_answers": [
                    [
                        "Red Bull Racing",
                        "+2016-01-01T00:00:00"
                    ]
                ],
                "match_type": [
                    "em"
                ],
                "correct_answer": "Red Bull Racing",
                "element": "Max Verstappen",
                "attribute": null
            },
            {
                "prediction": " Mercedes in Formula One.\n\n## Who is the best F1 driver 2020",
                "matched_answers": [
                    [
                        "Mercedes",
                        "+2013-01-01T00:00:00"
                    ]
                ],
                "match_type": [
                    "simplified"
                ],
                "correct_answer": "Mercedes F1 Team",
                "element": "Lewis Hamilton",
                "attribute": null
            },
            {
                "prediction": " Red Bull Racing in Formula One. He is the first Mexican driver to win a Formula One Grand Prix",
                "matched_answers": [
                    [
                        "Red Bull Racing",
                        "+2021-01-01T00:00:00"
                    ]
                ],
                "match_type": [
                    "em"
                ],
                "correct_answer": "Red Bull Racing",
                "element": "Sergio P\u00e9rez",
                "attribute": null
            },
            {
                "prediction": " Ferrari in Formula One. He is a Monegasque racing driver who is currently competing in",
                "matched_answers": [
                    [
                        "Ferrari",
                        "+2019-01-01T00:00:00"
                    ]
                ],
                "match_type": [
                    "simplified"
                ],
                "correct_answer": "Scuderia Ferrari",
                "element": "Charles Leclerc",
                "attribute": null
            },
            {
                "prediction": " McLaren in Formula One.\n\n## Who is the youngest F1 driver 20",
                "matched_answers": [
                    [
                        "McLaren",
                        "+2019-01-01T00:00:00"
                    ]
                ],
                "match_type": [
                    "em"
                ],
                "correct_answer": "McLaren",
                "element": "Lando Norris",
                "attribute": null
            },
            {
                "prediction": " Williams in Formula 1. He is a British racing driver who was born on February 15",
                "matched_answers": [
                    [
                        "Williams",
                        "+2019-01-01T00:00:00"
                    ]
                ],
                "match_type": [
                    "simplified"
                ],
                "correct_answer": "Williams Racing",
                "element": "George Russell",
                "attribute": null
            }
        ],
        "outdated": [
            {
                "prediction": " Juventus.\n\n## Who is the best player in the world?\n\nWho is",
                "matched_answers": [
                    [
                        "Juventus",
                        "+2018-01-01T00:00:00Z"
                    ]
                ],
                "match_type": [
                    "simplified"
                ],
                "correct_answer": "Al-Nassr",
                "element": "Cristiano Ronaldo",
                "attribute": null
            },
            {
                "prediction": " Barcelona.\n\n## Who is the best player in the world?\n\nWho is the best",
                "matched_answers": [
                    [
                        "Barcelona",
                        "+2004-01-01T00:00:00Z"
                    ]
                ],
                "match_type": [
                    "simplified"
                ],
                "correct_answer": "Inter Miami CF",
                "element": "Lionel Messi",
                "attribute": null
            },
            {
                "prediction": " the Brazilian national team and Paris Saint-Germain. He is a forward and is considered",
                "matched_answers": [
                    [
                        "Paris Saint-Germain",
                        "+2017-01-01T00:00:00Z"
                    ]
                ],
                "match_type": [
                    "simplified"
                ],
                "correct_answer": "Al-Hilal SFC",
                "element": "Neymar Jr.",
                "attribute": null
            },
            {
                "prediction": " Real Madrid.\n\n## Who is the best player in Real Madrid?\n\nThe 1",
                "matched_answers": [
                    [
                        "Real Madrid",
                        "+2009-01-01T00:00:00Z"
                    ]
                ],
                "match_type": [
                    "simplified"
                ],
                "correct_answer": "Al Ittihad FC",
                "element": "Karim Benzema",
                "attribute": null
            },
            {
                "prediction": " Borussia Dortmund.\n\n## Who is the best player in the world?\n\nWho",
                "matched_answers": [
                    [
                        "Borussia Dortmund",
                        "+2020-01-01T00:00:00Z"
                    ]
                ],
                "match_type": [
                    "em"
                ],
                "correct_answer": "Manchester City F.C.",
                "element": "Erling Haaland",
                "attribute": null
            },
            {
                "prediction": " Liverpool.\n\n## Who is the best player in Liverpool?\n\nLiverpool\u2019s",
                "matched_answers": [
                    [
                        "Liverpool",
                        "+2016-07-01T00:00:00Z"
                    ]
                ],
                "match_type": [
                    "simplified"
                ],
                "correct_answer": "Al-Nassr",
                "element": "Sadio Man\u00e9",
                "attribute": null
            },
            {
                "prediction": " Tottenham Hotspur.\n\n## Who is the best player in Tottenham?",
                "matched_answers": [
                    [
                        "Tottenham Hotspur",
                        "+2013-01-01T00:00:00Z"
                    ]
                ],
                "match_type": [
                    "simplified"
                ],
                "correct_answer": "FC Bayern Munich",
                "element": "Harry Kane",
                "attribute": null
            },
            {
                "prediction": " the Golden State Warriors.\n\n## Who is Kevin Durant playing for?\n\nK",
                "matched_answers": [
                    [
                        "Golden State Warriors",
                        "+2016-01-01T00:00:00Z"
                    ]
                ],
                "match_type": [
                    "em"
                ],
                "correct_answer": "Phoenix Suns",
                "element": "Kevin Durant",
                "attribute": null
            },
            {
                "prediction": " the Portland Trail Blazers.\n\n## Who is the best player on the Portland Trail Bl",
                "matched_answers": [
                    [
                        "Portland Trail Blazers",
                        "+2012-01-01T00:00:00Z"
                    ]
                ],
                "match_type": [
                    "em"
                ],
                "correct_answer": "Milwaukee Bucks",
                "element": "Damian Lillard",
                "attribute": null
            },
            {
                "prediction": " McLaren in Formula One. He is the son of the two-time World Rally Champion",
                "matched_answers": [
                    [
                        "McLaren",
                        "+2019-01-01T00:00:00Z"
                    ]
                ],
                "match_type": [
                    "em"
                ],
                "correct_answer": "Scuderia Ferrari",
                "element": "Carlos Sainz Jr.",
                "attribute": null
            }
        ],
        "irrelevant": [
            {
                "prediction": " the Washington Wizards.\n\n## Who is the best player on the Washington Wizards",
                "matched_answers": [],
                "match_type": [],
                "correct_answer": "Phoenix Suns",
                "element": "Bradley Beal",
                "attribute": null
            },
            {
                "prediction": " the Los Angeles Clippers.\n\n## Who is Kawhi Leonard\u2019s wife?",
                "matched_answers": [],
                "match_type": [],
                "correct_answer": "Toronto Raptors",
                "element": "Kawhi Leonard",
                "attribute": null
            },
            {
                "prediction": " the Oklahoma City Thunder.\n\n## Who is Paul George playing for?\n\nPaul George",
                "matched_answers": [],
                "match_type": [],
                "correct_answer": "Los Angeles Clippers",
                "element": "Paul George",
                "attribute": null
            },
            {
                "prediction": " the Alpine F1 Team.\n\n## Who is Fernando Alonso driving for in ",
                "matched_answers": [],
                "match_type": [],
                "correct_answer": "Aston Martin F1 Team",
                "element": "Fernando Alonso",
                "attribute": null
            },
            {
                "prediction": " Scuderia AlphaTauri in Formula One. He is a French racing driver who currently compet",
                "matched_answers": [],
                "match_type": [],
                "correct_answer": "Alpine F1 Team",
                "element": "Pierre Gasly",
                "attribute": null
            }
        ],
        "ambiguous": []
    },
    "rephrased_2": {
        "correct": [
            {
                "prediction": " Paris Saint-Germain.\n\n## What is the name of the football club of K",
                "matched_answers": [
                    [
                        "Paris Saint-Germain",
                        "+2018-01-01T00:00:00"
                    ]
                ],
                "match_type": [
                    "simplified"
                ],
                "correct_answer": "Paris Saint-Germain F.C.",
                "element": "Kylian Mbapp\u00e9",
                "attribute": null
            },
            {
                "prediction": " Liverpool.\n\n## What is the name of Mohamed Salah\u2019s football club?\n",
                "matched_answers": [
                    [
                        "Liverpool",
                        "+2017-01-01T00:00:00"
                    ]
                ],
                "match_type": [
                    "simplified"
                ],
                "correct_answer": "Liverpool F.C.",
                "element": "Mohamed Salah",
                "attribute": null
            },
            {
                "prediction": " Manchester City.\n\n## Who is the best player in the world?\n\nWho is the",
                "matched_answers": [
                    [
                        "Manchester City",
                        "+2015-01-01T00:00:00"
                    ]
                ],
                "match_type": [
                    "simplified"
                ],
                "correct_answer": "Manchester City F.C.",
                "element": "Kevin De Bruyne",
                "attribute": null
            },
            {
                "prediction": " the Golden State Warriors.\n\n## What team is Stephen Curry on 202",
                "matched_answers": [
                    [
                        "Golden State Warriors",
                        "+2009-06-25T00:00:00"
                    ]
                ],
                "match_type": [
                    "em"
                ],
                "correct_answer": "Golden State Warriors",
                "element": "Stephen Curry",
                "attribute": null
            },
            {
                "prediction": " the Los Angeles Lakers.\n\n## What team is LeBron James on 20",
                "matched_answers": [
                    [
                        "Los Angeles Lakers",
                        "+2018-07-09T00:00:00"
                    ]
                ],
                "match_type": [
                    "em"
                ],
                "correct_answer": "Los Angeles Lakers",
                "element": "LeBron James",
                "attribute": null
            },
            {
                "prediction": " the Denver Nuggets.\n\n## What team is Nikola Jokic on?\n",
                "matched_answers": [
                    [
                        "Denver Nuggets",
                        "+2015-01-01T00:00:00"
                    ]
                ],
                "match_type": [
                    "em"
                ],
                "correct_answer": "Denver Nuggets",
                "element": "Nikola Jokic",
                "attribute": null
            },
            {
                "prediction": " the Milwaukee Bucks.\n\n## What team is Giannis on?\n\n",
                "matched_answers": [
                    [
                        "Milwaukee Bucks",
                        "+2013-01-01T00:00:00"
                    ]
                ],
                "match_type": [
                    "em"
                ],
                "correct_answer": "Milwaukee Bucks",
                "element": "Giannis Antetokounmpo",
                "attribute": null
            },
            {
                "prediction": " Red Bull Racing.\n\n## What team is Max Verstappen in?\n\nMax Ver",
                "matched_answers": [
                    [
                        "Red Bull Racing",
                        "+2016-01-01T00:00:00"
                    ]
                ],
                "match_type": [
                    "em"
                ],
                "correct_answer": "Red Bull Racing",
                "element": "Max Verstappen",
                "attribute": null
            },
            {
                "prediction": " Mercedes.\n\n## What team is Lewis Hamilton on 2021?\n\nL",
                "matched_answers": [
                    [
                        "Mercedes",
                        "+2013-01-01T00:00:00"
                    ]
                ],
                "match_type": [
                    "simplified"
                ],
                "correct_answer": "Mercedes F1 Team",
                "element": "Lewis Hamilton",
                "attribute": null
            },
            {
                "prediction": " Red Bull Racing.\n\n## What team is Sergio Perez on?\n\nRed Bull",
                "matched_answers": [
                    [
                        "Red Bull Racing",
                        "+2021-01-01T00:00:00"
                    ]
                ],
                "match_type": [
                    "em"
                ],
                "correct_answer": "Red Bull Racing",
                "element": "Sergio P\u00e9rez",
                "attribute": null
            },
            {
                "prediction": " Ferrari.\n\n## What team is Charles Leclerc on?\n\nFerrari",
                "matched_answers": [
                    [
                        "Ferrari",
                        "+2019-01-01T00:00:00"
                    ]
                ],
                "match_type": [
                    "simplified"
                ],
                "correct_answer": "Scuderia Ferrari",
                "element": "Charles Leclerc",
                "attribute": null
            },
            {
                "prediction": " McLaren.\n\n## What team is Lando Norris in?\n\nMcL",
                "matched_answers": [
                    [
                        "McLaren",
                        "+2019-01-01T00:00:00"
                    ]
                ],
                "match_type": [
                    "em"
                ],
                "correct_answer": "McLaren",
                "element": "Lando Norris",
                "attribute": null
            },
            {
                "prediction": " Williams.\n\n## What team is George Russell in?\n\nGeorge Russell (racing",
                "matched_answers": [
                    [
                        "Williams",
                        "+2019-01-01T00:00:00"
                    ]
                ],
                "match_type": [
                    "simplified"
                ],
                "correct_answer": "Williams Racing",
                "element": "George Russell",
                "attribute": null
            }
        ],
        "outdated": [
            {
                "prediction": ":\n\n- Real Madrid\n- Manchester United\n- Juventus\n- Barcelona\n\n",
                "matched_answers": [
                    [
                        "Real Madrid",
                        "+2009-01-01T00:00:00Z"
                    ]
                ],
                "match_type": [
                    "simplified"
                ],
                "correct_answer": "Al-Nassr",
                "element": "Cristiano Ronaldo",
                "attribute": null
            },
            {
                "prediction": " Barcelona.\n\n## What is the name of the football club of Lionel Messi?\n",
                "matched_answers": [
                    [
                        "Barcelona",
                        "+2004-01-01T00:00:00Z"
                    ]
                ],
                "match_type": [
                    "simplified"
                ],
                "correct_answer": "Inter Miami CF",
                "element": "Lionel Messi",
                "attribute": null
            },
            {
                "prediction": " Paris Saint-Germain.\n\n## What is the name of Neymar\u2019s",
                "matched_answers": [
                    [
                        "Paris Saint-Germain",
                        "+2017-01-01T00:00:00Z"
                    ]
                ],
                "match_type": [
                    "simplified"
                ],
                "correct_answer": "Al-Hilal SFC",
                "element": "Neymar Jr.",
                "attribute": null
            },
            {
                "prediction": " Real Madrid.\n\n## Who is the best player in the world?\n\nWho is the",
                "matched_answers": [
                    [
                        "Real Madrid",
                        "+2009-01-01T00:00:00Z"
                    ]
                ],
                "match_type": [
                    "simplified"
                ],
                "correct_answer": "Al Ittihad FC",
                "element": "Karim Benzema",
                "attribute": null
            },
            {
                "prediction": " Borussia Dortmund.\n\n## What is the name of Erling Haaland\u2019s football",
                "matched_answers": [
                    [
                        "Borussia Dortmund",
                        "+2020-01-01T00:00:00Z"
                    ]
                ],
                "match_type": [
                    "em"
                ],
                "correct_answer": "Manchester City F.C.",
                "element": "Erling Haaland",
                "attribute": null
            },
            {
                "prediction": " Liverpool.\n\n## Which club is Sadio Mane?\n\nLiverpool F.",
                "matched_answers": [
                    [
                        "Liverpool",
                        "+2016-07-01T00:00:00Z"
                    ]
                ],
                "match_type": [
                    "simplified"
                ],
                "correct_answer": "Al-Nassr",
                "element": "Sadio Man\u00e9",
                "attribute": null
            },
            {
                "prediction": " Tottenham Hotspur.\n\n## Who is Harry Kane\u2019s current club?",
                "matched_answers": [
                    [
                        "Tottenham Hotspur",
                        "+2013-01-01T00:00:00Z"
                    ]
                ],
                "match_type": [
                    "simplified"
                ],
                "correct_answer": "FC Bayern Munich",
                "element": "Harry Kane",
                "attribute": null
            },
            {
                "prediction": " the Brooklyn Nets.\n\n## What team is Kevin Durant on 2021",
                "matched_answers": [
                    [
                        "Brooklyn Nets",
                        "+2019-01-01T00:00:00Z"
                    ]
                ],
                "match_type": [
                    "em"
                ],
                "correct_answer": "Phoenix Suns",
                "element": "Kevin Durant",
                "attribute": null
            },
            {
                "prediction": " the Portland Trail Blazers.\n\n## What team is Damian Lillard on?",
                "matched_answers": [
                    [
                        "Portland Trail Blazers",
                        "+2012-01-01T00:00:00Z"
                    ]
                ],
                "match_type": [
                    "em"
                ],
                "correct_answer": "Milwaukee Bucks",
                "element": "Damian Lillard",
                "attribute": null
            },
            {
                "prediction": ":\n\n- A. Ferrari\n- B. McLaren\n- C. Ren",
                "matched_answers": [
                    [
                        "Ferrari",
                        "+2010-01-01T00:00:00Z"
                    ]
                ],
                "match_type": [
                    "simplified"
                ],
                "correct_answer": "Aston Martin F1 Team",
                "element": "Fernando Alonso",
                "attribute": null
            },
            {
                "prediction": " McLaren.\n\n## What team is Carlos Sainz Jr in?\n\nC",
                "matched_answers": [
                    [
                        "McLaren",
                        "+2019-01-01T00:00:00Z"
                    ]
                ],
                "match_type": [
                    "em"
                ],
                "correct_answer": "Scuderia Ferrari",
                "element": "Carlos Sainz Jr.",
                "attribute": null
            },
            {
                "prediction": ":\n\n- A. Red Bull\n- B. Toro Rosso\n- C.",
                "matched_answers": [
                    [
                        "Red Bull",
                        "+2019-01-01T00:00:00Z"
                    ]
                ],
                "match_type": [
                    "simplified"
                ],
                "correct_answer": "Alpine F1 Team",
                "element": "Pierre Gasly",
                "attribute": null
            }
        ],
        "irrelevant": [
            {
                "prediction": " the Washington Wizards.\n\n## What team is Bradley Beal on?\n\n",
                "matched_answers": [],
                "match_type": [],
                "correct_answer": "Phoenix Suns",
                "element": "Bradley Beal",
                "attribute": null
            },
            {
                "prediction": " the Los Angeles Clippers.\n\n## What team is Kawhi Leonard on 2",
                "matched_answers": [],
                "match_type": [],
                "correct_answer": "Toronto Raptors",
                "element": "Kawhi Leonard",
                "attribute": null
            },
            {
                "prediction": " the Oklahoma City Thunder.\n\n## What team is Paul George on 2020",
                "matched_answers": [],
                "match_type": [],
                "correct_answer": "Los Angeles Clippers",
                "element": "Paul George",
                "attribute": null
            }
        ],
        "ambiguous": []
    }
}