{
    "Brazil": {
        "President of Brazil": {
            "generic": "+2023-01-01T00:00:00Z",
            "rephrased_2": "+2019-01-01T00:00:00Z"
        }
    },
    "Norway": {
        "Monarch of Norway": {
            "generic": "+1991-01-17T00:00:00Z",
            "rephrased_1": "+1991-01-17T00:00:00Z",
            "rephrased_2": "+1991-01-17T00:00:00Z"
        },
        "Prime Minister of Norway": {
            "rephrased_1": "+2005-10-17T00:00:00Z",
            "rephrased_2": "+2013-10-16T00:00:00Z"
        }
    },
    "India": {
        "President of India": {
            "generic": "+2017-07-25T00:00:00Z",
            "rephrased_2": "+2017-07-25T00:00:00Z"
        },
        "Prime minister of India": {
            "contextualized": "+2014-05-26T00:00:00Z",
            "rephrased_1": "+2004-05-22T00:00:00Z",
            "rephrased_2": "+2014-05-26T00:00:00Z"
        }
    },
    "United Kingdom": {
        "monarch of the United Kingdom": {
            "generic": "+1952-02-06T00:00:00Z",
            "rephrased_2": "+1952-02-06T00:00:00Z"
        },
        "Prime Minister of the United Kingdom": {
            "rephrased_1": "+2019-07-24T00:00:00Z",
            "rephrased_2": "+2016-07-13T00:00:00Z"
        }
    },
    "Russia": {
        "President of Russia": {
            "generic": "+1991-07-10T00:00:00Z",
            "rephrased_2": "+2012-05-07T00:00:00Z"
        },
        "Prime Minister of Russia": {
            "generic": "+2008-05-08T00:00:00Z",
            "rephrased_1": "+2008-05-08T00:00:00Z",
            "rephrased_2": "+2012-05-08T00:00:00Z"
        }
    },
    "United Arab Emirates": {
        "President of the United Arab Emirates": {
            "generic": "+2004-11-03T00:00:00Z",
            "rephrased_2": "+2004-11-03T00:00:00Z"
        }
    },
    "Czech Republic": {
        "President of the Czech Republic": {
            "generic": "+1993-02-02T00:00:00Z",
            "rephrased_2": "+2003-03-07T00:00:00Z"
        },
        "Prime Minister of the Czech Republic": {
            "rephrased_1": "+2014-01-29T00:00:00Z",
            "rephrased_2": "+2006-08-16T00:00:00Z"
        }
    },
    "United States of America": {
        "President of the United States": {
            "contextualized": "+2009-01-20T00:00:00Z",
            "rephrased_1": "+2009-01-20T00:00:00Z",
            "rephrased_2": "+2017-01-20T00:00:00Z"
        }
    },
    "Pakistan": {
        "Prime Minister of Pakistan": {
            "contextualized": "+2013-06-05T00:00:00Z",
            "rephrased_1": "+2018-08-18T00:00:00Z",
            "rephrased_2": "+2013-06-05T00:00:00Z"
        }
    },
    "Italy": {
        "President of Italy": {
            "rephrased_1": "+2015-02-03T00:00:00Z",
            "rephrased_2": "+2015-02-03T00:00:00Z"
        },
        "Prime Minister of Italy": {
            "rephrased_1": "+2014-02-22T00:00:00Z",
            "rephrased_2": "+2014-02-22T00:00:00Z"
        }
    },
    "China": {
        "President of the People's Republic of China": {
            "rephrased_1": "+2013-03-14T00:00:00Z",
            "rephrased_2": "+2013-03-14T00:00:00Z"
        },
        "Premier of the People's Republic of China": {
            "rephrased_2": "+2013-03-15T00:00:00Z"
        }
    },
    "Netherlands": {
        "King of the Netherlands": {
            "rephrased_1": "+2013-04-30T00:00:00Z",
            "rephrased_2": "+2013-04-30T00:00:00Z"
        },
        "Prime Minister of the Netherlands": {
            "rephrased_1": "+2010-10-14T00:00:00Z",
            "rephrased_2": "+2010-10-14T00:00:00Z"
        }
    },
    "Saudi Arabia": {
        "King of Saudi Arabia": {
            "rephrased_1": "+2015-01-23T00:00:00Z",
            "rephrased_2": "+2015-01-23T00:00:00Z"
        }
    },
    "Belgium": {
        "Monarch of the Belgians": {
            "rephrased_1": "+2013-07-21T00:00:00Z",
            "rephrased_2": "+2013-07-21T00:00:00Z"
        }
    },
    "Israel": {
        "Prime Minister of Israel": {
            "rephrased_1": "+2022-12-29T00:00:00Z",
            "rephrased_2": "+2022-12-29T00:00:00Z"
        },
        "President of Israel": {
            "rephrased_2": "+2000-08-01T00:00:00Z"
        }
    },
    "Thailand": {
        "King of Thailand": {
            "rephrased_1": "+2016-12-01T00:00:00Z",
            "rephrased_2": "+2016-12-01T00:00:00Z"
        }
    },
    "Bangladesh": {
        "Prime Minister of Bangladesh": {
            "rephrased_1": "+2009-01-06T00:00:00Z",
            "rephrased_2": "+2009-01-06T00:00:00Z"
        },
        "President of Bangladesh": {
            "rephrased_2": "+2013-04-14T00:00:00Z"
        }
    },
    "Iran": {
        "Supreme Leader of Iran": {
            "rephrased_1": "+1989-06-04T00:00:00Z",
            "rephrased_2": "+1989-06-04T00:00:00Z"
        },
        "President of Iran": {
            "rephrased_1": "+2013-08-03T00:00:00Z",
            "rephrased_2": "+2013-08-03T00:00:00Z"
        }
    },
    "Romania": {
        "President of Romania": {
            "rephrased_1": "+2014-12-21T00:00:00Z",
            "rephrased_2": "+2014-12-21T00:00:00Z"
        },
        "Prime Minister of Romania": {
            "rephrased_1": "+2018-01-29T00:00:00Z",
            "rephrased_2": "+2017-01-04T00:00:00Z"
        }
    },
    "Portugal": {
        "President of Portugal": {
            "rephrased_1": "+2016-03-09T00:00:00Z",
            "rephrased_2": "+2006-03-09T00:00:00Z"
        },
        "Prime Minister of Portugal": {
            "rephrased_2": "+2011-06-21T00:00:00Z"
        }
    },
    "Germany": {
        "Federal Chancellor of Germany": {
            "rephrased_1": "+2005-11-22T00:00:00Z",
            "rephrased_2": "+2005-11-22T00:00:00Z"
        },
        "president of Germany": {
            "rephrased_2": "+2012-03-18T00:00:00Z"
        }
    },
    "Japan": {
        "Emperor of Japan": {
            "rephrased_1": "+1989-01-07T00:00:00Z",
            "rephrased_2": "+2019-05-01T00:00:00Z"
        },
        "Prime Minister of Japan": {
            "rephrased_1": "+2020-09-16T00:00:00Z",
            "rephrased_2": "+2012-12-26T00:00:00Z"
        }
    },
    "France": {
        "Prime Minister of France": {
            "rephrased_1": "+2014-03-31T00:00:00Z"
        },
        "President of the French Republic": {
            "rephrased_2": "+2017-05-14T00:00:00Z"
        }
    },
    "Canada": {
        "monarch of Canada": {
            "rephrased_1": "+1952-02-06T00:00:00Z",
            "rephrased_2": "+1952-02-06T00:00:00Z"
        },
        "Prime Minister of Canada": {
            "rephrased_1": "+2006-02-06T00:00:00Z",
            "rephrased_2": "+2015-11-04T00:00:00Z"
        }
    },
    "Mexico": {
        "President of Mexico": {
            "rephrased_1": "+2012-12-01T00:00:00Z",
            "rephrased_2": "+2006-12-01T00:00:00Z"
        }
    },
    "South Korea": {
        "President of South Korea": {
            "rephrased_1": "+2013-02-25T00:00:00Z",
            "rephrased_2": "+2017-05-10T00:00:00Z"
        }
    },
    "Australia": {
        "monarch of Australia": {
            "rephrased_1": "+1952-02-06T00:00:00Z",
            "rephrased_2": "+1952-02-06T00:00:00Z"
        },
        "Prime Minister of Australia": {
            "rephrased_1": "+2015-09-15T00:00:00Z",
            "rephrased_2": "+2018-08-24T00:00:00Z"
        }
    },
    "Indonesia": {
        "President of Indonesia": {
            "rephrased_1": "+2004-10-20T00:00:00Z",
            "rephrased_2": "+2014-10-20T00:00:00Z"
        }
    },
    "Turkey": {
        "President of Turkey": {
            "rephrased_1": "+2007-08-28T00:00:00Z",
            "rephrased_2": "+2014-08-28T00:00:00Z"
        },
        "Prime Minister of Turkey": {
            "rephrased_1": "+2014-08-28T00:00:00Z"
        }
    },
    "Poland": {
        "President of the Republic of Poland": {
            "rephrased_1": "+2010-08-06T00:00:00Z",
            "rephrased_2": "+2015-08-06T00:00:00Z"
        },
        "Prime Minister of Poland": {
            "rephrased_1": "+2017-12-11T00:00:00Z",
            "rephrased_2": "+2017-12-11T00:00:00Z"
        }
    },
    "Philippines": {
        "President of the Philippines": {
            "rephrased_1": "+1986-02-25T00:00:00Z",
            "rephrased_2": "+2016-06-30T00:00:00Z"
        }
    },
    "Vietnam": {
        "President of Vietnam": {
            "rephrased_1": "+2016-04-02T00:00:00Z",
            "rephrased_2": "+2016-04-02T00:00:00Z"
        }
    },
    "Denmark": {
        "Prime Minister of Denmark": {
            "rephrased_1": "+2015-06-28T00:00:00Z",
            "rephrased_2": "+2001-11-27T00:00:00Z"
        },
        "monarch of Denmark": {
            "rephrased_2": "+1972-01-14T00:00:00Z"
        }
    },
    "Nigeria": {
        "President of Nigeria": {
            "rephrased_1": "+2015-05-29T00:00:00Z",
            "rephrased_2": "+2015-05-29T00:00:00Z"
        }
    },
    "South Africa": {
        "President of South Africa": {
            "rephrased_1": "+2009-05-09T00:00:00Z",
            "rephrased_2": "+2009-05-09T00:00:00Z"
        }
    },
    "Chile": {
        "President of Chile": {
            "rephrased_1": "+2014-03-11T00:00:00Z",
            "rephrased_2": "+2014-03-11T00:00:00Z"
        }
    },
    "Spain": {
        "Monarch of Spain": {
            "rephrased_2": "+2014-06-19T00:00:00Z"
        },
        "Prime Minister of Spain": {
            "rephrased_2": "+2011-12-21T00:00:00Z"
        }
    },
    "Sweden": {
        "Monarch of Sweden": {
            "rephrased_2": "+1973-09-15T00:00:00Z"
        },
        "Prime Minister of Sweden": {
            "rephrased_2": "+2014-10-03T00:00:00Z"
        }
    },
    "Ireland": {
        "President of Ireland": {
            "rephrased_2": "+2011-11-11T00:00:00Z"
        }
    },
    "Egypt": {
        "Prime Minister of Egypt": {
            "rephrased_2": "+2018-06-14T00:00:00Z"
        }
    },
    "Austria": {
        "Federal Chancellor of Austria": {
            "rephrased_2": "+2020-01-07T00:00:00Z"
        }
    },
    "Malaysia": {
        "Prime Minister of Malaysia": {
            "rephrased_2": "+2018-05-10T00:00:00Z"
        }
    },
    "Colombia": {
        "President of Colombia": {
            "rephrased_2": "+2018-08-07T00:00:00Z"
        }
    }
}